{"availability":1,"classification":2,"computation_units":"\u043f\u0440\u043e\u0446\u0435\u043d\u0442","customisation":"meta.customisation-3","data_non_statistical":false,"goal_meta_link_text":"United Nations Sustainable Development Goals Metadata (PDF 4.0 MB)","graph_title":"meta.name-2-4-1","graph_type":"line","indicator":"2.4.1","indicator_name":"meta.name-2-4-1","indicator_sort_order":"02-04-01","layout":"indicator","national_geographical_coverage":"\u041a\u0430\u0437\u0430\u0445\u0441\u0442\u0430\u043d","permalink":"/2-4-1/","published":true,"reporting_status":"complete","sdg_goal":"2","source_active_1":true,"source_compilation_1":"\u041c\u0438\u043d\u0438\u0441\u0442\u0435\u0440\u0441\u0442\u0432\u043e \u0441\u0435\u043b\u044c\u0441\u043a\u043e\u0433\u043e \u0445\u043e\u0437\u044f\u0439\u0441\u0442\u0432\u0430 \u0420\u041a","source_data_1":null,"source_implementation_1":"\u041c\u0438\u043d\u0438\u0441\u0442\u0435\u0440\u0441\u0442\u0432\u043e \u0441\u0435\u043b\u044c\u0441\u043a\u043e\u0433\u043e \u0445\u043e\u0437\u044f\u0439\u0441\u0442\u0432\u0430 \u0420\u041a","tags":[],"target":"By 2030, ensure sustainable food production systems and implement resilient agricultural practices that increase productivity and production, that help maintain ecosystems, that strengthen capacity for adaptation to climate change, extreme weather, drought, flooding and other disasters and that progressively improve land and soil quality","target_id":"2.4","un_custodian_agency":"Food and Agriculture Organization (FAO)","un_designated_tier":"3","national_data_update_url_text":"2019-05-18: see changes on GitHub","national_data_update_url":"https://github.com/kazstat/sdg-data-kazstat/commit/9667e8c5e00978b8c656b02b304f8d6ab1c74c3f","national_metadata_update_url_text":"2019-06-10: see changes on GitHub","national_metadata_update_url":"https://github.com/kazstat/sdg-data-kazstat/commit/ad7a24975306c98e00c93ec6c230c57a43d83870","page_content":""}